pyboon/__init__.py
pyboon/chain.py
pyboon/convert.py
pyboon/datetime2.py
pyboon/file.py
pyboon/json2.py
pyboon/print2.py
pyboon/qs.py
pyboon/rest.py
pyboon/sql.py
pyboon/trans.py
pyboon/underscore.py
pyboon/x.py
test/__init__.py
test/test_chain.py
test/test_convert.py
test/test_datatime2.py
test/test_json2.py
test/test_qs.py
test/test_rest.py
test/test_sql.py
test/test_underscore.py
test/test_x.py
pyboon-0.0.20.dist-info/LICENSE
pyboon-0.0.20.dist-info/METADATA
pyboon-0.0.20.dist-info/WHEEL
pyboon-0.0.20.dist-info/top_level.txt
pyboon-0.0.20.dist-info/RECORD
